{
  "version": "7",
  "dialect": "postgresql",
  "entries": [
    {
      "idx": 0,
      "version": "7",
      "when": 1757382533404,
      "tag": "0000_violet_pete_wisdom",
      "breakpoints": true
    },
    {
      "idx": 3,
      "version": "7",
      "when": 1756778270320,
      "tag": "0003_cool_skrulls",
      "breakpoints": true
    },
    {
      "idx": 4,
      "version": "7",
      "when": 1760380431165,
      "tag": "0004_famous_mulholland_black",
      "breakpoints": true
    }
  ]
}